bloomrpyc/__init__.py
bloomrpyc/main.py
bloomrpyc-0.0.2.dist-info/METADATA
bloomrpyc-0.0.2.dist-info/WHEEL
bloomrpyc-0.0.2.dist-info/top_level.txt
bloomrpyc-0.0.2.dist-info/RECORD
