Metadata-Version: 2.1
Name: bloomrpyc
Version: 0.0.2
Summary: bloomrpyc
Author: Jinho Kim
Author-email: sauron9973@gmail.com
License: MIT
Platform: UNKNOWN
Classifier: Programming Language :: Python :: 3
Classifier: License :: OSI Approved :: MIT License
Classifier: Operating System :: OS Independent
